{"assets":[{"id":"comp_3","layers":[{"ddd":0,"ind":0,"ty":4,"nm":"Creative Designer Outlines","ks":{"o":{"k":100},"r":{"k":0},"p":{"k":[943.8,480,0]},"a":{"k":[133.612,-14.059,0]},"s":{"k":[100,100,100]}},"ao":0,"shapes":[{"ty":"gr","it":[{"ind":0,"ty":"sh","ks":{"k":{"i":[[0,0],[0.806,-0.765],[3.062,0],[1.249,1.249],[0,3.706],[-2.256,2.175],[-2.256,0],[-1.128,-1.168],[-0.161,-1.893],[0,0],[1.41,1.37],[2.981,0],[1.853,-1.813],[0,-3.907],[-2.86,-2.981],[-2.9,0],[-2.618,2.618],[-0.322,2.699]],"o":[[-0.201,2.82],[-1.088,1.007],[-3.263,0],[-2.538,-2.457],[0,-3.948],[2.095,-2.014],[3.223,0],[1.007,1.047],[0,0],[-0.161,-2.659],[-2.216,-2.175],[-4.351,0],[-3.062,3.021],[0,4.028],[2.9,3.021],[2.78,0],[1.772,-1.772],[0,0]],"v":[[24.492,-9.185],[22.035,-3.907],[15.952,-1.692],[9.305,-4.23],[5.841,-14.583],[9.144,-24.049],[15.872,-26.506],[22.156,-24.25],[24.17,-19.739],[27.191,-19.739],[24.452,-26.063],[15.63,-29.044],[6.606,-25.62],[2.659,-14.139],[6.566,-2.659],[15.751,0.846],[24.25,-2.135],[27.513,-9.185]],"c":true}},"nm":"C","mn":"ADBE Vector Shape - Group"},{"ty":"fl","c":{"k":[0,0,0,1]},"o":{"k":100},"nm":"Fill 1","mn":"ADBE Vector Graphic - Fill"},{"ty":"tr","p":{"k":[0,0],"ix":2},"a":{"k":[0,0],"ix":1},"s":{"k":[100,100],"ix":3},"r":{"k":0,"ix":6},"o":{"k":100,"ix":7},"sk":{"k":0,"ix":4},"sa":{"k":0,"ix":5},"nm":"Transform"}],"nm":"C","np":3,"mn":"ADBE Vector Group"},{"ty":"gr","it":[{"ind":0,"ty":"sh","ks":{"k":{"i":[[0,0],[0,0],[0,0],[0,0],[-0.874,-0.733],[-0.056,-1.354],[0,0],[-0.197,-0.31],[0,0],[0.028,0.677],[0,0],[1.072,1.043],[0.931,0.226],[0,0],[-0.761,0.846],[0,1.269],[0.649,0.677],[2.171,0],[0,0]],"o":[[0,0],[0,0],[0,0],[0.733,0],[0.959,0.818],[0,0],[0.056,1.579],[0,0],[-0.733,-1.1],[0,0],[-0.028,-1.269],[-0.226,-0.226],[0,0],[0.649,-0.169],[0.902,-1.043],[0,-1.833],[-1.297,-1.354],[0,0],[0,0]],"v":[[33.914,0],[36,0],[36,-8.685],[42.232,-8.685],[45.052,-7.896],[46.039,-4.653],[46.124,-2.566],[46.772,0],[49.028,0],[48.267,-2.735],[48.21,-4.963],[47.11,-8.629],[45.39,-9.587],[45.39,-9.644],[47.646,-11.054],[48.831,-14.55],[47.477,-18.216],[42.289,-19.739],[33.914,-19.739]],"c":true}},"nm":"r","mn":"ADBE Vector Shape - Group"},{"ind":1,"ty":"sh","ks":{"k":{"i":[[0,0],[0,0],[-1.015,-0.902],[0,-1.382],[0.649,-0.62],[1.297,0],[0,0]],"o":[[0,0],[0.931,0],[0.508,0.423],[0,1.213],[-0.761,0.705],[0,0],[0,0]],"v":[[36,-17.962],[41.978,-17.962],[45.588,-17.06],[46.603,-14.438],[45.503,-11.505],[42.091,-10.462],[36,-10.462]],"c":true}},"nm":"r","mn":"ADBE Vector Shape - Group"},{"ty":"mm","mm":1,"nm":"Merge Paths 1","mn":"ADBE Vector Filter - Merge"},{"ty":"fl","c":{"k":[0,0,0,1]},"o":{"k":100},"nm":"Fill 1","mn":"ADBE Vector Graphic - Fill"},{"ty":"tr","p":{"k":[0,0],"ix":2},"a":{"k":[0,0],"ix":1},"s":{"k":[100,100],"ix":3},"r":{"k":0,"ix":6},"o":{"k":100,"ix":7},"sk":{"k":0,"ix":4},"sa":{"k":0,"ix":5},"nm":"Transform"}],"nm":"r","np":5,"mn":"ADBE Vector Group"},{"ty":"gr","it":[{"ind":0,"ty":"sh","ks":{"k":{"i":[[0,0],[0,0],[0,0],[0,0],[0,0],[0,0],[0,0],[0,0],[0,0],[0,0],[0,0],[0,0]],"o":[[0,0],[0,0],[0,0],[0,0],[0,0],[0,0],[0,0],[0,0],[0,0],[0,0],[0,0],[0,0]],"v":[[56.832,-11.11],[56.832,-17.962],[68.365,-17.962],[68.365,-19.739],[54.745,-19.739],[54.745,0],[68.703,0],[68.703,-1.776],[56.832,-1.776],[56.832,-9.334],[67.378,-9.334],[67.378,-11.11]],"c":true}},"nm":"e","mn":"ADBE Vector Shape - Group"},{"ty":"fl","c":{"k":[0,0,0,1]},"o":{"k":100},"nm":"Fill 1","mn":"ADBE Vector Graphic - Fill"},{"ty":"tr","p":{"k":[0,0],"ix":2},"a":{"k":[0,0],"ix":1},"s":{"k":[100,100],"ix":3},"r":{"k":0,"ix":6},"o":{"k":100,"ix":7},"sk":{"k":0,"ix":4},"sa":{"k":0,"ix":5},"nm":"Transform"}],"nm":"e","np":3,"mn":"ADBE Vector Group"},{"ty":"gr","it":[{"ind":0,"ty":"sh","ks":{"k":{"i":[[0,0],[0,0],[0,0],[0,0],[0,0],[0,0],[0,0],[0,0]],"o":[[0,0],[0,0],[0,0],[0,0],[0,0],[0,0],[0,0],[0,0]],"v":[[76.01,-5.668],[84.611,-5.668],[86.697,0],[88.981,0],[81.481,-19.739],[79.14,-19.739],[71.639,0],[73.895,0]],"c":true}},"nm":"a","mn":"ADBE Vector Shape - Group"},{"ind":1,"ty":"sh","ks":{"k":{"i":[[0,0],[0,0],[0,0]],"o":[[0,0],[0,0],[0,0]],"v":[[76.602,-7.444],[80.296,-17.737],[83.99,-7.444]],"c":true}},"nm":"a","mn":"ADBE Vector Shape - Group"},{"ty":"mm","mm":1,"nm":"Merge Paths 1","mn":"ADBE Vector Filter - Merge"},{"ty":"fl","c":{"k":[0,0,0,1]},"o":{"k":100},"nm":"Fill 1","mn":"ADBE Vector Graphic - Fill"},{"ty":"tr","p":{"k":[0,0],"ix":2},"a":{"k":[0,0],"ix":1},"s":{"k":[100,100],"ix":3},"r":{"k":0,"ix":6},"o":{"k":100,"ix":7},"sk":{"k":0,"ix":4},"sa":{"k":0,"ix":5},"nm":"Transform"}],"nm":"a","np":5,"mn":"ADBE Vector Group"},{"ty":"gr","it":[{"ind":0,"ty":"sh","ks":{"k":{"i":[[0,0],[0,0],[0,0],[0,0],[0,0],[0,0],[0,0],[0,0]],"o":[[0,0],[0,0],[0,0],[0,0],[0,0],[0,0],[0,0],[0,0]],"v":[[95.318,-17.962],[95.318,0],[97.404,0],[97.404,-17.962],[103.946,-17.962],[103.946,-19.739],[88.776,-19.739],[88.776,-17.962]],"c":true}},"nm":"t","mn":"ADBE Vector Shape - Group"},{"ty":"fl","c":{"k":[0,0,0,1]},"o":{"k":100},"nm":"Fill 1","mn":"ADBE Vector Graphic - Fill"},{"ty":"tr","p":{"k":[0,0],"ix":2},"a":{"k":[0,0],"ix":1},"s":{"k":[100,100],"ix":3},"r":{"k":0,"ix":6},"o":{"k":100,"ix":7},"sk":{"k":0,"ix":4},"sa":{"k":0,"ix":5},"nm":"Transform"}],"nm":"t","np":3,"mn":"ADBE Vector Group"},{"ty":"gr","it":[{"ind":0,"ty":"sh","ks":{"k":{"i":[[0,0],[0,0],[0,0],[0,0]],"o":[[0,0],[0,0],[0,0],[0,0]],"v":[[108,-19.739],[108,0],[110.087,0],[110.087,-19.739]],"c":true}},"nm":"i","mn":"ADBE Vector Shape - Group"},{"ty":"fl","c":{"k":[0,0,0,1]},"o":{"k":100},"nm":"Fill 1","mn":"ADBE Vector Graphic - Fill"},{"ty":"tr","p":{"k":[0,0],"ix":2},"a":{"k":[0,0],"ix":1},"s":{"k":[100,100],"ix":3},"r":{"k":0,"ix":6},"o":{"k":100,"ix":7},"sk":{"k":0,"ix":4},"sa":{"k":0,"ix":5},"nm":"Transform"}],"nm":"i","np":3,"mn":"ADBE Vector Group"},{"ty":"gr","it":[{"ind":0,"ty":"sh","ks":{"k":{"i":[[0,0],[0,0],[0,0],[0,0],[0,0],[0,0],[0,0]],"o":[[0,0],[0,0],[0,0],[0,0],[0,0],[0,0],[0,0]],"v":[[122.405,-2.143],[116.427,-19.739],[114.143,-19.739],[121.108,0],[123.674,0],[130.639,-19.739],[128.355,-19.739]],"c":true}},"nm":"v","mn":"ADBE Vector Shape - Group"},{"ty":"fl","c":{"k":[0,0,0,1]},"o":{"k":100},"nm":"Fill 1","mn":"ADBE Vector Graphic - Fill"},{"ty":"tr","p":{"k":[0,0],"ix":2},"a":{"k":[0,0],"ix":1},"s":{"k":[100,100],"ix":3},"r":{"k":0,"ix":6},"o":{"k":100,"ix":7},"sk":{"k":0,"ix":4},"sa":{"k":0,"ix":5},"nm":"Transform"}],"nm":"v","np":3,"mn":"ADBE Vector Group"},{"ty":"gr","it":[{"ind":0,"ty":"sh","ks":{"k":{"i":[[0,0],[0,0],[0,0],[0,0],[0,0],[0,0],[0,0],[0,0],[0,0],[0,0],[0,0],[0,0]],"o":[[0,0],[0,0],[0,0],[0,0],[0,0],[0,0],[0,0],[0,0],[0,0],[0,0],[0,0],[0,0]],"v":[[136.715,-11.11],[136.715,-17.962],[148.248,-17.962],[148.248,-19.739],[134.628,-19.739],[134.628,0],[148.586,0],[148.586,-1.776],[136.715,-1.776],[136.715,-9.334],[147.261,-9.334],[147.261,-11.11]],"c":true}},"nm":"e","mn":"ADBE Vector Shape - Group"},{"ty":"fl","c":{"k":[0,0,0,1]},"o":{"k":100},"nm":"Fill 1","mn":"ADBE Vector Graphic - Fill"},{"ty":"tr","p":{"k":[0,0],"ix":2},"a":{"k":[0,0],"ix":1},"s":{"k":[100,100],"ix":3},"r":{"k":0,"ix":6},"o":{"k":100,"ix":7},"sk":{"k":0,"ix":4},"sa":{"k":0,"ix":5},"nm":"Transform"}],"nm":"e","np":3,"mn":"ADBE Vector Group"},{"ty":"gr","it":[{"ind":0,"ty":"sh","ks":{"k":{"i":[[0,0],[0,0],[0,0],[-2.82,2.538],[0,5.156],[1.974,1.893],[2.9,0]],"o":[[0,0],[0,0],[3.263,0],[2.377,-2.175],[0,-5.64],[-2.981,-2.82],[0,0]],"v":[[165.567,-28.198],[165.567,0],[175.034,0],[184.742,-2.981],[188.73,-14.18],[184.822,-25.096],[175.436,-28.198]],"c":true}},"nm":"D","mn":"ADBE Vector Shape - Group"},{"ind":1,"ty":"sh","ks":{"k":{"i":[[0,0],[0,0],[-2.256,-2.216],[0,-3.867],[1.934,-1.934],[2.377,0],[0,0]],"o":[[0,0],[2.135,0],[2.014,1.974],[0,3.706],[-2.618,2.578],[0,0],[0,0]],"v":[[168.548,-25.66],[175.396,-25.66],[182.486,-23.163],[185.588,-14.099],[182.647,-5.156],[174.147,-2.538],[168.548,-2.538]],"c":true}},"nm":"D","mn":"ADBE Vector Shape - Group"},{"ty":"mm","mm":1,"nm":"Merge Paths 1","mn":"ADBE Vector Filter - Merge"},{"ty":"fl","c":{"k":[0,0,0,1]},"o":{"k":100},"nm":"Fill 1","mn":"ADBE Vector Graphic - Fill"},{"ty":"tr","p":{"k":[0,0],"ix":2},"a":{"k":[0,0],"ix":1},"s":{"k":[100,100],"ix":3},"r":{"k":0,"ix":6},"o":{"k":100,"ix":7},"sk":{"k":0,"ix":4},"sa":{"k":0,"ix":5},"nm":"Transform"}],"nm":"D","np":5,"mn":"ADBE Vector Group"},{"ty":"gr","it":[{"ind":0,"ty":"sh","ks":{"k":{"i":[[0,0],[0,0],[0,0],[0,0],[0,0],[0,0],[0,0],[0,0],[0,0],[0,0],[0,0],[0,0]],"o":[[0,0],[0,0],[0,0],[0,0],[0,0],[0,0],[0,0],[0,0],[0,0],[0,0],[0,0],[0,0]],"v":[[197.341,-11.11],[197.341,-17.962],[208.874,-17.962],[208.874,-19.739],[195.255,-19.739],[195.255,0],[209.213,0],[209.213,-1.776],[197.341,-1.776],[197.341,-9.334],[207.887,-9.334],[207.887,-11.11]],"c":true}},"nm":"e","mn":"ADBE Vector Shape - Group"},{"ty":"fl","c":{"k":[0,0,0,1]},"o":{"k":100},"nm":"Fill 1","mn":"ADBE Vector Graphic - Fill"},{"ty":"tr","p":{"k":[0,0],"ix":2},"a":{"k":[0,0],"ix":1},"s":{"k":[100,100],"ix":3},"r":{"k":0,"ix":6},"o":{"k":100,"ix":7},"sk":{"k":0,"ix":4},"sa":{"k":0,"ix":5},"nm":"Transform"}],"nm":"e","np":3,"mn":"ADBE Vector Group"},{"ty":"gr","it":[{"ind":0,"ty":"sh","ks":{"k":{"i":[[0,0],[-0.846,-0.846],[-2.03,0],[-1.635,1.495],[0,1.805],[0.733,0.705],[2.143,0.423],[0,0],[0.79,0.818],[0,0.987],[-1.043,0.649],[-0.423,0],[-0.931,-0.846],[-0.113,-1.156],[0,0],[0.254,0.254],[2.876,0],[1.748,-1.128],[0,-2.058],[-0.564,-0.62],[-1.664,-0.31],[0,0],[-0.931,-0.987],[0,-0.931],[0.649,-0.62],[1.607,0],[1.128,1.156],[-0.028,1.635]],"o":[[0,2.256],[1.805,1.805],[1.495,0],[1.043,-0.959],[0,-1.805],[-1.184,-1.128],[0,0],[-1.354,-0.254],[-0.338,-0.367],[0,-1.184],[1.156,-0.705],[1.438,0],[0.649,0.592],[0,0],[-0.197,-2.312],[-0.874,-0.846],[-0.79,0],[-1.354,0.874],[0,1.523],[1.241,1.354],[0,0],[0.818,0.141],[0.479,0.536],[0,1.072],[-0.931,0.902],[-1.579,0],[-0.592,-0.592],[0,0]],"v":[[212.663,-6.232],[214.496,-1.523],[220.868,0.536],[226.452,-1.156],[228.143,-5.414],[226.705,-9.052],[221.517,-11.11],[219.656,-11.477],[216.159,-12.915],[215.398,-14.889],[217.033,-17.821],[220.333,-18.583],[224.224,-17.427],[225.521,-14.691],[227.608,-14.691],[225.888,-18.554],[220.502,-20.359],[215.567,-19.175],[213.198,-14.748],[214.355,-11.618],[219.317,-9.503],[221.291,-9.136],[225.07,-7.557],[225.944,-5.217],[224.844,-2.566],[220.671,-1.241],[216.075,-2.848],[214.778,-6.232]],"c":true}},"nm":"s","mn":"ADBE Vector Shape - Group"},{"ty":"fl","c":{"k":[0,0,0,1]},"o":{"k":100},"nm":"Fill 1","mn":"ADBE Vector Graphic - Fill"},{"ty":"tr","p":{"k":[0,0],"ix":2},"a":{"k":[0,0],"ix":1},"s":{"k":[100,100],"ix":3},"r":{"k":0,"ix":6},"o":{"k":100,"ix":7},"sk":{"k":0,"ix":4},"sa":{"k":0,"ix":5},"nm":"Transform"}],"nm":"s","np":3,"mn":"ADBE Vector Group"},{"ty":"gr","it":[{"ind":0,"ty":"sh","ks":{"k":{"i":[[0,0],[0,0],[0,0],[0,0]],"o":[[0,0],[0,0],[0,0],[0,0]],"v":[[233.502,-19.739],[233.502,0],[235.589,0],[235.589,-19.739]],"c":true}},"nm":"i","mn":"ADBE Vector Shape - Group"},{"ty":"fl","c":{"k":[0,0,0,1]},"o":{"k":100},"nm":"Fill 1","mn":"ADBE Vector Graphic - Fill"},{"ty":"tr","p":{"k":[0,0],"ix":2},"a":{"k":[0,0],"ix":1},"s":{"k":[100,100],"ix":3},"r":{"k":0,"ix":6},"o":{"k":100,"ix":7},"sk":{"k":0,"ix":4},"sa":{"k":0,"ix":5},"nm":"Transform"}],"nm":"i","np":3,"mn":"ADBE Vector Group"},{"ty":"gr","it":[{"ind":0,"ty":"sh","ks":{"k":{"i":[[0,0],[0,0],[0,0],[1.495,-1.438],[2.115,0],[0.987,1.072],[0,2.876],[-1.946,2.058],[-2.763,0],[-1.015,-1.043],[-0.169,-1.213],[0,0],[1.072,1.015],[2.876,0],[1.043,-1.043],[0,-4.032],[-0.733,-0.761],[-2.312,0],[-1.466,1.043],[-0.536,1.072],[0,0],[0,0],[0,0],[0,0]],"o":[[0,0],[0,0],[0,1.805],[-0.874,0.846],[-2.34,0],[-1.382,-1.466],[0,-1.269],[0.79,-0.846],[1.833,0],[0.649,0.649],[0,0],[-0.226,-1.692],[-1.072,-1.015],[-3.581,0],[-1.382,1.382],[0,4.991],[1.805,1.917],[1.41,0],[0.931,-0.677],[0,0],[0,0],[0,0],[0,0],[0,0]],"v":[[250.642,-10.123],[250.642,-8.347],[256.789,-8.347],[254.787,-2.876],[250.36,-1.184],[245.482,-3.186],[243.226,-9.954],[245.341,-16.693],[250.445,-18.611],[254.956,-17.004],[256.31,-14.071],[258.397,-14.071],[256.31,-18.413],[250.473,-20.387],[243.79,-18.019],[241.026,-9.982],[243.762,-1.776],[250.022,0.592],[254.59,-0.62],[256.93,-3.468],[256.987,-3.468],[256.987,0],[258.735,0],[258.735,-10.123]],"c":true}},"nm":"g","mn":"ADBE Vector Shape - Group"},{"ty":"fl","c":{"k":[0,0,0,1]},"o":{"k":100},"nm":"Fill 1","mn":"ADBE Vector Graphic - Fill"},{"ty":"tr","p":{"k":[0,0],"ix":2},"a":{"k":[0,0],"ix":1},"s":{"k":[100,100],"ix":3},"r":{"k":0,"ix":6},"o":{"k":100,"ix":7},"sk":{"k":0,"ix":4},"sa":{"k":0,"ix":5},"nm":"Transform"}],"nm":"g","np":3,"mn":"ADBE Vector Group"},{"ty":"gr","it":[{"ind":0,"ty":"sh","ks":{"k":{"i":[[0,0],[0,0],[0,0],[0,0],[0,0],[0,0],[0,0],[0,0],[0,0],[0,0]],"o":[[0,0],[0,0],[0,0],[0,0],[0,0],[0,0],[0,0],[0,0],[0,0],[0,0]],"v":[[266.529,-16.609],[277.639,0],[280.007,0],[280.007,-19.739],[277.921,-19.739],[277.921,-3.13],[266.839,-19.739],[264.442,-19.739],[264.442,0],[266.529,0]],"c":true}},"nm":"n","mn":"ADBE Vector Shape - Group"},{"ty":"fl","c":{"k":[0,0,0,1]},"o":{"k":100},"nm":"Fill 1","mn":"ADBE Vector Graphic - Fill"},{"ty":"tr","p":{"k":[0,0],"ix":2},"a":{"k":[0,0],"ix":1},"s":{"k":[100,100],"ix":3},"r":{"k":0,"ix":6},"o":{"k":100,"ix":7},"sk":{"k":0,"ix":4},"sa":{"k":0,"ix":5},"nm":"Transform"}],"nm":"n","np":3,"mn":"ADBE Vector Group"},{"ty":"gr","it":[{"ind":0,"ty":"sh","ks":{"k":{"i":[[0,0],[0,0],[0,0],[0,0],[0,0],[0,0],[0,0],[0,0],[0,0],[0,0],[0,0],[0,0]],"o":[[0,0],[0,0],[0,0],[0,0],[0,0],[0,0],[0,0],[0,0],[0,0],[0,0],[0,0],[0,0]],"v":[[288.536,-11.11],[288.536,-17.962],[300.07,-17.962],[300.07,-19.739],[286.45,-19.739],[286.45,0],[300.408,0],[300.408,-1.776],[288.536,-1.776],[288.536,-9.334],[299.083,-9.334],[299.083,-11.11]],"c":true}},"nm":"e","mn":"ADBE Vector Shape - Group"},{"ty":"fl","c":{"k":[0,0,0,1]},"o":{"k":100},"nm":"Fill 1","mn":"ADBE Vector Graphic - Fill"},{"ty":"tr","p":{"k":[0,0],"ix":2},"a":{"k":[0,0],"ix":1},"s":{"k":[100,100],"ix":3},"r":{"k":0,"ix":6},"o":{"k":100,"ix":7},"sk":{"k":0,"ix":4},"sa":{"k":0,"ix":5},"nm":"Transform"}],"nm":"e","np":3,"mn":"ADBE Vector Group"},{"ty":"gr","it":[{"ind":0,"ty":"sh","ks":{"k":{"i":[[0,0],[0,0],[0,0],[0,0],[-0.874,-0.733],[-0.056,-1.354],[0,0],[-0.197,-0.31],[0,0],[0.028,0.677],[0,0],[1.072,1.043],[0.931,0.226],[0,0],[-0.761,0.846],[0,1.269],[0.649,0.677],[2.171,0],[0,0]],"o":[[0,0],[0,0],[0,0],[0.733,0],[0.959,0.818],[0,0],[0.056,1.579],[0,0],[-0.733,-1.1],[0,0],[-0.028,-1.269],[-0.226,-0.226],[0,0],[0.649,-0.169],[0.902,-1.043],[0,-1.833],[-1.297,-1.354],[0,0],[0,0]],"v":[[304.958,0],[307.044,0],[307.044,-8.685],[313.276,-8.685],[316.096,-7.896],[317.083,-4.653],[317.167,-2.566],[317.816,0],[320.072,0],[319.311,-2.735],[319.254,-4.963],[318.154,-8.629],[316.434,-9.587],[316.434,-9.644],[318.69,-11.054],[319.874,-14.55],[318.521,-18.216],[313.332,-19.739],[304.958,-19.739]],"c":true}},"nm":"r","mn":"ADBE Vector Shape - Group"},{"ind":1,"ty":"sh","ks":{"k":{"i":[[0,0],[0,0],[-1.015,-0.902],[0,-1.382],[0.649,-0.62],[1.297,0],[0,0]],"o":[[0,0],[0.931,0],[0.508,0.423],[0,1.213],[-0.761,0.705],[0,0],[0,0]],"v":[[307.044,-17.962],[313.022,-17.962],[316.632,-17.06],[317.647,-14.438],[316.547,-11.505],[313.135,-10.462],[307.044,-10.462]],"c":true}},"nm":"r","mn":"ADBE Vector Shape - Group"},{"ty":"mm","mm":1,"nm":"Merge Paths 1","mn":"ADBE Vector Filter - Merge"},{"ty":"fl","c":{"k":[0,0,0,1]},"o":{"k":100},"nm":"Fill 1","mn":"ADBE Vector Graphic - Fill"},{"ty":"tr","p":{"k":[0,0],"ix":2},"a":{"k":[0,0],"ix":1},"s":{"k":[100,100],"ix":3},"r":{"k":0,"ix":6},"o":{"k":100,"ix":7},"sk":{"k":0,"ix":4},"sa":{"k":0,"ix":5},"nm":"Transform"}],"nm":"r","np":5,"mn":"ADBE Vector Group"}],"ip":0,"op":300,"st":0,"bm":0,"sr":1}]},{"id":"comp_4","layers":[{"ddd":0,"ind":0,"ty":4,"nm":"Hafiz .O Outlines","cl":"O","ks":{"o":{"k":100},"r":{"k":0},"p":{"k":[911.4,540,0]},"a":{"k":[342.308,-31.859,0]},"s":{"k":[100,100,100]}},"ao":0,"shapes":[{"ty":"gr","it":[{"ind":0,"ty":"sh","ks":{"k":{"i":[[0,0],[0,0],[0,0],[0,0],[0,0],[0,0],[0,0],[0,0],[0,0],[0,0],[0,0],[0,0]],"o":[[0,0],[0,0],[0,0],[0,0],[0,0],[0,0],[0,0],[0,0],[0,0],[0,0],[0,0],[0,0]],"v":[[15.323,-28.163],[45.455,-28.163],[45.455,0],[53.501,0],[53.501,-59.921],[45.455,-59.921],[45.455,-34.926],[15.323,-34.926],[15.323,-59.921],[7.276,-59.921],[7.276,0],[15.323,0]],"c":true}},"nm":"H","mn":"ADBE Vector Shape - Group"},{"ty":"fl","c":{"k":[0,0,0,1]},"o":{"k":100},"nm":"Fill 1","mn":"ADBE Vector Graphic - Fill"},{"ty":"tr","p":{"k":[0,0],"ix":2},"a":{"k":[0,0],"ix":1},"s":{"k":[100,100],"ix":3},"r":{"k":0,"ix":6},"o":{"k":100,"ix":7},"sk":{"k":0,"ix":4},"sa":{"k":0,"ix":5},"nm":"Transform"}],"nm":"H","np":3,"mn":"ADBE Vector Group"},{"ty":"gr","it":[{"ind":0,"ty":"sh","ks":{"k":{"i":[[0,0],[0,0],[0,0],[0,0],[0,0],[0,0],[0,0],[0,0]],"o":[[0,0],[0,0],[0,0],[0,0],[0,0],[0,0],[0,0],[0,0]],"v":[[78.552,-15.494],[103.891,-15.494],[109.54,0],[118.186,0],[95.502,-59.921],[86.941,-59.921],[64.257,0],[72.903,0]],"c":true}},"nm":"a","mn":"ADBE Vector Shape - Group"},{"ind":1,"ty":"sh","ks":{"k":{"i":[[0,0],[0,0],[0,0]],"o":[[0,0],[0,0],[0,0]],"v":[[80.778,-22.256],[91.221,-51.789],[101.665,-22.256]],"c":true}},"nm":"a","mn":"ADBE Vector Shape - Group"},{"ty":"mm","mm":1,"nm":"Merge Paths 1","mn":"ADBE Vector Filter - Merge"},{"ty":"fl","c":{"k":[0,0,0,1]},"o":{"k":100},"nm":"Fill 1","mn":"ADBE Vector Graphic - Fill"},{"ty":"tr","p":{"k":[0,0],"ix":2},"a":{"k":[0,0],"ix":1},"s":{"k":[100,100],"ix":3},"r":{"k":0,"ix":6},"o":{"k":100,"ix":7},"sk":{"k":0,"ix":4},"sa":{"k":0,"ix":5},"nm":"Transform"}],"nm":"a","np":5,"mn":"ADBE Vector Group"},{"ty":"gr","it":[{"ind":0,"ty":"sh","ks":{"k":{"i":[[0,0],[0,0],[0,0],[0,0],[0,0],[0,0],[0,0],[0,0],[0,0],[0,0]],"o":[[0,0],[0,0],[0,0],[0,0],[0,0],[0,0],[0,0],[0,0],[0,0],[0,0]],"v":[[137.041,-33.642],[137.041,-53.159],[169.228,-53.159],[169.228,-59.921],[128.995,-59.921],[128.995,0],[137.041,0],[137.041,-26.879],[165.204,-26.879],[165.204,-33.642]],"c":true}},"nm":"f","mn":"ADBE Vector Shape - Group"},{"ty":"fl","c":{"k":[0,0,0,1]},"o":{"k":100},"nm":"Fill 1","mn":"ADBE Vector Graphic - Fill"},{"ty":"tr","p":{"k":[0,0],"ix":2},"a":{"k":[0,0],"ix":1},"s":{"k":[100,100],"ix":3},"r":{"k":0,"ix":6},"o":{"k":100,"ix":7},"sk":{"k":0,"ix":4},"sa":{"k":0,"ix":5},"nm":"Transform"}],"nm":"f","np":3,"mn":"ADBE Vector Group"},{"ty":"gr","it":[{"ind":0,"ty":"sh","ks":{"k":{"i":[[0,0],[0,0],[0,0],[0,0]],"o":[[0,0],[0,0],[0,0],[0,0]],"v":[[181.524,-59.921],[181.524,0],[189.571,0],[189.571,-59.921]],"c":true}},"nm":"i","mn":"ADBE Vector Shape - Group"},{"ty":"fl","c":{"k":[0,0,0,1]},"o":{"k":100},"nm":"Fill 1","mn":"ADBE Vector Graphic - Fill"},{"ty":"tr","p":{"k":[0,0],"ix":2},"a":{"k":[0,0],"ix":1},"s":{"k":[100,100],"ix":3},"r":{"k":0,"ix":6},"o":{"k":100,"ix":7},"sk":{"k":0,"ix":4},"sa":{"k":0,"ix":5},"nm":"Transform"}],"nm":"i","np":3,"mn":"ADBE Vector Group"},{"ty":"gr","it":[{"ind":0,"ty":"sh","ks":{"k":{"i":[[0,0],[0,0],[0,0],[0,0],[0,0],[0,0],[0,0],[0,0],[0,0],[0,0]],"o":[[0,0],[0,0],[0,0],[0,0],[0,0],[0,0],[0,0],[0,0],[0,0],[0,0]],"v":[[205.046,-59.921],[205.046,-53.159],[238.346,-53.159],[203.163,-7.362],[203.163,0],[249.474,0],[249.474,-6.763],[213.007,-6.763],[247.762,-53.501],[247.762,-59.921]],"c":true}},"nm":"z","mn":"ADBE Vector Shape - Group"},{"ty":"fl","c":{"k":[0,0,0,1]},"o":{"k":100},"nm":"Fill 1","mn":"ADBE Vector Graphic - Fill"},{"ty":"tr","p":{"k":[0,0],"ix":2},"a":{"k":[0,0],"ix":1},"s":{"k":[100,100],"ix":3},"r":{"k":0,"ix":6},"o":{"k":100,"ix":7},"sk":{"k":0,"ix":4},"sa":{"k":0,"ix":5},"nm":"Transform"}],"nm":"z","np":3,"mn":"ADBE Vector Group"},{"ty":"gr","it":[{"ind":0,"ty":"sh","ks":{"k":{"i":[[0,0],[0,0],[0,0],[0,0]],"o":[[0,0],[0,0],[0,0],[0,0]],"v":[[288.719,0],[297.194,0],[297.194,-9.331],[288.719,-9.331]],"c":true}},"nm":".","mn":"ADBE Vector Shape - Group"},{"ty":"fl","c":{"k":[1,0.76,0.07,1]},"o":{"k":100},"nm":"Fill 1","mn":"ADBE Vector Graphic - Fill"},{"ty":"tr","p":{"k":[0,0],"ix":2},"a":{"k":[0,0],"ix":1},"s":{"k":[100,100],"ix":3},"r":{"k":0,"ix":6},"o":{"k":100,"ix":7},"sk":{"k":0,"ix":4},"sa":{"k":0,"ix":5},"nm":"Transform"}],"nm":".","np":3,"mn":"ADBE Vector Group"},{"ty":"gr","it":[{"ind":0,"ty":"sh","ks":{"k":{"i":[[0,-20.972],[-3.938,0],[0,31.33],[13.268,0]],"o":[[0,31.33],[3.681,0],[0,-24.397],[-16.692,0]],"v":[[314.181,-29.961],[342.772,1.798],[371.363,-29.961],[342.772,-61.719]],"c":true}},"nm":"O","mn":"ADBE Vector Shape - Group"},{"ind":1,"ty":"sh","ks":{"k":{"i":[[0,9.673],[-18.319,0],[0,-14.124],[4.109,0]],"o":[[0,-6.506],[13.782,0],[0,24.14],[-17.12,0]],"v":[[322.742,-29.961],[342.772,-54.956],[362.803,-29.961],[342.772,-4.965]],"c":true}},"nm":"O","mn":"ADBE Vector Shape - Group"},{"ty":"mm","mm":1,"nm":"Merge Paths 1","mn":"ADBE Vector Filter - Merge"},{"ty":"fl","c":{"k":[0,0,0,1]},"o":{"k":100},"nm":"Fill 1","mn":"ADBE Vector Graphic - Fill"},{"ty":"tr","p":{"k":[0,0],"ix":2},"a":{"k":[0,0],"ix":1},"s":{"k":[100,100],"ix":3},"r":{"k":0,"ix":6},"o":{"k":100,"ix":7},"sk":{"k":0,"ix":4},"sa":{"k":0,"ix":5},"nm":"Transform"}],"nm":"O","np":5,"mn":"ADBE Vector Group"}],"ip":0,"op":300,"st":0,"bm":0,"sr":1}]},{"id":"comp_5","layers":[{"ddd":0,"ind":0,"ty":1,"nm":"White Solid 1","ks":{"o":{"k":100},"r":{"k":0},"p":{"k":[960,540,0]},"a":{"k":[960,540,0]},"s":{"k":[100,100,100]}},"ao":0,"sw":1920,"sh":1080,"sc":"#ffffff","ip":0,"op":300,"st":0,"bm":0,"sr":1},{"ddd":0,"ind":1,"ty":1,"nm":"Black Solid 6","ks":{"o":{"k":100},"r":{"k":0},"p":{"k":[960,540,0]},"a":{"k":[960,540,0]},"s":{"k":[100,100,100]}},"ao":0,"hasMask":true,"masksProperties":[{"inv":true,"mode":"a","pt":{"k":{"i":[[530.193,0],[0,-298.234],[-530.193,0],[0,298.234]],"o":[[-530.193,0],[0,298.234],[530.193,0],[0,-298.234]],"v":[[960,0],[0,540],[960,1080],[1920,540]],"c":true}},"o":{"k":71},"x":{"k":0},"nm":"Mask 1"}],"sw":1920,"sh":1080,"sc":"#000000","ip":0,"op":300,"st":0,"bm":0,"sr":1}]}],"layers":[{"ddd":0,"ind":0,"ty":4,"nm":"Shape Layer 1","ks":{"o":{"k":100},"r":{"k":0},"p":{"k":[540,540,0]},"a":{"k":[0,0,0]},"s":{"k":[100,100,100]}},"ao":0,"shapes":[{"ty":"gr","it":[{"ty":"rc","d":1,"s":{"k":[487,10]},"p":{"k":[0,0]},"r":{"k":0},"nm":"Rectangle Path 1","mn":"ADBE Vector Shape - Rect"},{"ty":"fl","c":{"k":[1,0.76,0.07,1]},"o":{"k":100},"nm":"Fill 1","mn":"ADBE Vector Graphic - Fill"},{"ty":"tr","p":{"k":[-252.5,-29],"ix":2},"a":{"k":[-245,0],"ix":1},"s":{"k":[{"i":{"x":[0,0.667],"y":[1,0.667]},"o":{"x":[1,0.333],"y":[0,0.333]},"n":["0_1_1_0","0p667_0p667_0p333_0p333"],"t":0,"s":[0,100],"e":[100,100]},{"t":50}],"ix":3},"r":{"k":0,"ix":6},"o":{"k":100,"ix":7},"sk":{"k":0,"ix":4},"sa":{"k":0,"ix":5},"nm":"Transform"}],"nm":"Rectangle 1","np":3,"mn":"ADBE Vector Group"}],"ip":0,"op":300,"st":0,"bm":0,"sr":1},{"ddd":0,"ind":1,"ty":3,"nm":"Position and Scale","ks":{"o":{"k":0},"r":{"k":0},"p":{"k":[547,523,0]},"a":{"k":[50,50,0]},"s":{"k":[100,100,100]}},"ao":0,"ip":0,"op":300,"st":0,"bm":0,"sr":1},{"ddd":0,"ind":2,"ty":4,"nm":"Line","parent":1,"ks":{"o":{"k":100},"r":{"k":0},"p":{"k":[41,47,0]},"a":{"k":[0,0,0]},"s":{"k":[100,100,100]}},"ao":0,"ef":[{"ty":21,"nm":"Fill","mn":"ADBE Fill","ix":1,"ef":[{"ty":3,"nm":"Fill Mask","mn":"ADBE Fill-0001","ix":1,"v":{"k":0}},{"ty":7,"nm":"All Masks","mn":"ADBE Fill-0007","ix":2,"v":{"k":0}},{"ty":2,"nm":"Color","mn":"ADBE Fill-0002","ix":3,"v":{"k":[1,0,0,1]}},{"ty":7,"nm":"Invert","mn":"ADBE Fill-0006","ix":4,"v":{"k":0}},{"ty":0,"nm":"Horizontal Feather","mn":"ADBE Fill-0003","ix":5,"v":{"k":0}},{"ty":0,"nm":"Vertical Feather","mn":"ADBE Fill-0004","ix":6,"v":{"k":0}},{"ty":0,"nm":"Opacity","mn":"ADBE Fill-0005","ix":7,"v":{"k":0}}]}],"shapes":[{"ty":"gr","it":[{"ind":0,"ty":"sh","ks":{"k":{"i":[[0,0],[0,0]],"o":[[0,0],[0,0]],"v":[[-340,-100],[429.5,-100]],"c":false}},"nm":"Path 1","mn":"ADBE Vector Shape - Group"},{"ty":"st","c":{"k":[0.21,0.54,0.89,1]},"o":{"k":100},"w":{"k":15},"lc":1,"lj":1,"ml":4,"nm":"Stroke 1","mn":"ADBE Vector Graphic - Stroke"},{"ty":"fl","c":{"k":[1,0,0,1]},"o":{"k":100},"nm":"Fill 1","mn":"ADBE Vector Graphic - Fill"},{"ty":"tr","p":{"k":[0,0],"ix":2},"a":{"k":[0,0],"ix":1},"s":{"k":[100,100],"ix":3},"r":{"k":0,"ix":6},"o":{"k":100,"ix":7},"sk":{"k":0,"ix":4},"sa":{"k":0,"ix":5},"nm":"Transform"}],"nm":"Shape 1","np":3,"mn":"ADBE Vector Group"},{"ty":"tm","s":{"k":0,"ix":1},"e":{"k":[{"i":{"x":[0.1],"y":[1]},"o":{"x":[0.3],"y":[0]},"n":["0p1_1_0p3_0"],"t":0,"s":[0],"e":[100]},{"t":50}],"ix":2},"o":{"k":0,"ix":3},"m":1,"ix":2,"nm":"Trim Paths 1","mn":"ADBE Vector Filter - Trim"}],"ip":0,"op":300,"st":0,"bm":0,"sr":1},{"ddd":0,"ind":3,"ty":4,"nm":"mask 2","parent":1,"td":1,"ks":{"o":{"k":100},"r":{"k":0},"p":{"k":[55,47,0]},"a":{"k":[0,0,0]},"s":{"k":[100,100,100]}},"ao":0,"shapes":[{"ty":"gr","it":[{"ty":"rc","d":1,"s":{"k":[912,1272]},"p":{"k":[0,0]},"r":{"k":0},"nm":"Rectangle Path 1","mn":"ADBE Vector Shape - Rect"},{"ty":"fl","c":{"k":[1,0,0,1]},"o":{"k":100},"nm":"Fill 1","mn":"ADBE Vector Graphic - Fill"},{"ty":"tr","p":{"k":[-812,-4],"ix":2},"a":{"k":[0,0],"ix":1},"s":{"k":[100,100],"ix":3},"r":{"k":0,"ix":6},"o":{"k":100,"ix":7},"sk":{"k":0,"ix":4},"sa":{"k":0,"ix":5},"nm":"Transform"}],"nm":"Rectangle 1","np":3,"mn":"ADBE Vector Group"}],"ip":0,"op":300,"st":0,"bm":0,"sr":1},{"ddd":0,"ind":4,"ty":0,"nm":"Text_02","tt":2,"refId":"comp_3","ks":{"o":{"k":100},"r":{"k":0},"p":{"k":[{"i":{"x":0.1,"y":1},"o":{"x":1,"y":0},"n":"0p1_1_1_0","t":30,"s":[-139.876,682.841,0],"e":[431.38,682.841,0],"to":[95.2093353271484,0,0],"ti":[-95.2093353271484,0,0]},{"t":50}]},"a":{"k":[960,540,0]},"s":{"k":[96.96,96.96,100]}},"ao":0,"w":1920,"h":1080,"ip":0,"op":300,"st":0,"bm":0,"sr":1},{"ddd":0,"ind":5,"ty":4,"nm":"mask","parent":1,"td":1,"ks":{"o":{"k":100},"r":{"k":0},"p":{"k":[55,47,0]},"a":{"k":[0,0,0]},"s":{"k":[100,100,100]}},"ao":0,"shapes":[{"ty":"gr","it":[{"ty":"rc","d":1,"s":{"k":[912,1272]},"p":{"k":[0,0]},"r":{"k":0},"nm":"Rectangle Path 1","mn":"ADBE Vector Shape - Rect"},{"ty":"fl","c":{"k":[1,0,0,1]},"o":{"k":100},"nm":"Fill 1","mn":"ADBE Vector Graphic - Fill"},{"ty":"tr","p":{"k":[-812,-4],"ix":2},"a":{"k":[0,0],"ix":1},"s":{"k":[100,100],"ix":3},"r":{"k":0,"ix":6},"o":{"k":100,"ix":7},"sk":{"k":0,"ix":4},"sa":{"k":0,"ix":5},"nm":"Transform"}],"nm":"Rectangle 1","np":3,"mn":"ADBE Vector Group"}],"ip":0,"op":300,"st":0,"bm":0,"sr":1},{"ddd":0,"ind":6,"ty":0,"nm":"Text_01","tt":2,"refId":"comp_4","ks":{"o":{"k":100},"r":{"k":0},"p":{"k":[{"i":{"x":0.1,"y":1},"o":{"x":1,"y":0},"n":"0p1_1_1_0","t":0,"s":[-505.832,560.139,0],"e":[695.781,560.139,0],"to":[200.268859863281,0,0],"ti":[-200.268859863281,0,0]},{"t":50}]},"a":{"k":[960,540,0]},"s":{"k":[105.722,105.722,100]}},"ao":0,"w":1920,"h":1080,"ip":0,"op":300,"st":0,"bm":0,"sr":1},{"ddd":0,"ind":7,"ty":0,"nm":"BG","refId":"comp_5","ks":{"o":{"k":100},"r":{"k":0},"p":{"k":[540,540,0]},"a":{"k":[960,540,0]},"s":{"k":[100,100,100]}},"ao":0,"w":1920,"h":1080,"ip":0,"op":300,"st":0,"bm":0,"sr":1}],"v":"4.5.4","ddd":0,"ip":0,"op":61,"fr":30,"w":1080,"h":1080}